ean/__init__.py
ean/ean.py
ean-0.0.2.dist-info/LICENSE
ean-0.0.2.dist-info/METADATA
ean-0.0.2.dist-info/WHEEL
ean-0.0.2.dist-info/top_level.txt
ean-0.0.2.dist-info/RECORD
